java_bytecode_disassembler/__init__.py
java_bytecode_disassembler/java_bytecode_disassembler.py
java_bytecode_disassembler-1.0.3.dist-info/LICENSE
java_bytecode_disassembler-1.0.3.dist-info/METADATA
java_bytecode_disassembler-1.0.3.dist-info/WHEEL
java_bytecode_disassembler-1.0.3.dist-info/top_level.txt
java_bytecode_disassembler-1.0.3.dist-info/RECORD
